cratedb_about/__init__.py
cratedb_about/cli.py
cratedb_about/settings.py
cratedb_about/util.py
cratedb_about/bundle/__init__.py
cratedb_about/bundle/llmstxt.py
cratedb_about/bundle/readme.md
cratedb_about/bundle/util.py
cratedb_about/outline/__init__.py
cratedb_about/outline/core.py
cratedb_about/outline/cratedb-outline.yaml
cratedb_about/outline/model.py
cratedb_about/prompt/__init__.py
cratedb_about/prompt/instructions.md
cratedb_about/query/__init__.py
cratedb_about/query/core.py
cratedb_about/query/model.py
cratedb_about-0.0.10.dist-info/licenses/LICENSE
cratedb_about-0.0.10.dist-info/METADATA
cratedb_about-0.0.10.dist-info/WHEEL
cratedb_about-0.0.10.dist-info/entry_points.txt
cratedb_about-0.0.10.dist-info/top_level.txt
cratedb_about-0.0.10.dist-info/RECORD
