Metadata-Version: 2.4
Name: cratedb-about
Version: 0.0.10
Summary: Information about CrateDB, for humans and machines.
Author: CrateDB Engineering
License-Expression: Apache-2.0
Project-URL: Changelog, https://github.com/crate/about/blob/main/CHANGES.md
Project-URL: Issues, https://github.com/crate/about/issues
Project-URL: Repository, https://github.com/crate/about
Keywords: cratedb,knowledge base
Classifier: Development Status :: 1 - Planning
Classifier: Environment :: Console
Classifier: Intended Audience :: Customer Service
Classifier: Intended Audience :: Developers
Classifier: Intended Audience :: Education
Classifier: Intended Audience :: End Users/Desktop
Classifier: Intended Audience :: Information Technology
Classifier: Intended Audience :: Manufacturing
Classifier: Intended Audience :: Science/Research
Classifier: Intended Audience :: System Administrators
Classifier: Intended Audience :: Telecommunications Industry
Classifier: Operating System :: MacOS :: MacOS X
Classifier: Operating System :: Microsoft :: Windows
Classifier: Operating System :: POSIX :: Linux
Classifier: Operating System :: Unix
Classifier: Programming Language :: Python
Classifier: Programming Language :: Python :: 3 :: Only
Classifier: Programming Language :: Python :: 3.9
Classifier: Programming Language :: Python :: 3.10
Classifier: Programming Language :: Python :: 3.11
Classifier: Programming Language :: Python :: 3.12
Classifier: Programming Language :: Python :: 3.13
Classifier: Programming Language :: Python :: 3.14
Classifier: Topic :: Adaptive Technologies
Classifier: Topic :: Communications
Classifier: Topic :: Database
Classifier: Topic :: Documentation
Classifier: Topic :: Education
Classifier: Topic :: Internet
Classifier: Topic :: Internet :: WWW/HTTP
Classifier: Topic :: Office/Business
Classifier: Topic :: Scientific/Engineering
Classifier: Topic :: Software Development :: Libraries
Classifier: Topic :: Software Development :: Pre-processors
Classifier: Topic :: Software Development :: Quality Assurance
Classifier: Topic :: Software Development :: Testing
Classifier: Topic :: Software Development :: Version Control
Classifier: Topic :: System :: Archiving
Classifier: Topic :: System :: Clustering
Classifier: Topic :: System :: Distributed Computing
Classifier: Topic :: System :: Logging
Classifier: Topic :: System :: Monitoring
Classifier: Topic :: System :: Networking
Classifier: Topic :: System :: Systems Administration
Classifier: Topic :: Text Processing
Classifier: Topic :: Utilities
Requires-Python: >=3.9
License-File: LICENSE
Requires-Dist: cattrs[pyyaml]<26
Requires-Dist: click<9
Requires-Dist: colorlog<7
Requires-Dist: hishel<0.2
Requires-Dist: llms-txt==0.0.4
Requires-Dist: markdown<4
Requires-Dist: platformdirs<5
Requires-Dist: pueblo<0.1
Requires-Dist: requests<3
Requires-Dist: tiktoken<0.13
Provides-Extra: all
Requires-Dist: cratedb-about[llm,manyio]; extra == "all"
Provides-Extra: develop
Requires-Dist: mypy<1.20; extra == "develop"
Requires-Dist: poethepoet<1; extra == "develop"
Requires-Dist: pyproject-fmt<3; extra == "develop"
Requires-Dist: ruff<0.15; extra == "develop"
Requires-Dist: validate-pyproject<1; extra == "develop"
Provides-Extra: llm
Requires-Dist: anthropic<0.76; extra == "llm"
Requires-Dist: claudette<0.4; extra == "llm"
Requires-Dist: openai<3; extra == "llm"
Provides-Extra: manyio
Requires-Dist: pueblo[fileio]; extra == "manyio"
Provides-Extra: release
Requires-Dist: build<2; extra == "release"
Requires-Dist: twine<7; extra == "release"
Provides-Extra: test
Requires-Dist: pytest<9; extra == "test"
Requires-Dist: pytest-cov<8; extra == "test"
Requires-Dist: pytest-mock<4; extra == "test"
Requires-Dist: requests-mock<2; extra == "test"
Dynamic: license-file
